PyOpenColorIO/_tool_wrapper.py
PyOpenColorIO/__init__.py
PyOpenColorIO/PyOpenColorIO.so
PyOpenColorIO/tools/ocioarchive
PyOpenColorIO/tools/ociocheck
PyOpenColorIO/tools/ociobakelut
PyOpenColorIO/tools/ociolutimage
PyOpenColorIO/tools/ociochecklut
PyOpenColorIO/tools/ociomakeclf
PyOpenColorIO/tools/ocioperf
PyOpenColorIO/tools/ociowrite
PyOpenColorIO/tools/ocioconvert
oiio_python-3.0.10.0.1.dist-info/RECORD
oiio_python-3.0.10.0.1.dist-info/WHEEL
oiio_python-3.0.10.0.1.dist-info/entry_points.txt
oiio_python-3.0.10.0.1.dist-info/top_level.txt
oiio_python-3.0.10.0.1.dist-info/METADATA
oiio_python-3.0.10.0.1.dist-info/licenses/LICENSE
oiio_python-3.0.10.0.1.dist-info/licenses/licenses/libpng-LICENSE
oiio_python-3.0.10.0.1.dist-info/licenses/licenses/fmt-LICENSE
oiio_python-3.0.10.0.1.dist-info/licenses/licenses/pybind11-LICENSE
oiio_python-3.0.10.0.1.dist-info/licenses/licenses/libheif-LICENSE
oiio_python-3.0.10.0.1.dist-info/licenses/licenses/libjpeg-LICENSE
oiio_python-3.0.10.0.1.dist-info/licenses/licenses/imath-LICENSE
oiio_python-3.0.10.0.1.dist-info/licenses/licenses/ptex-LICENSE
oiio_python-3.0.10.0.1.dist-info/licenses/licenses/openjpeg-LICENSE
oiio_python-3.0.10.0.1.dist-info/licenses/licenses/openimageio-LICENSE
oiio_python-3.0.10.0.1.dist-info/licenses/licenses/onetbb-LICENSE
oiio_python-3.0.10.0.1.dist-info/licenses/licenses/hdf5-LICENSE
oiio_python-3.0.10.0.1.dist-info/licenses/licenses/freetype-LICENSE
oiio_python-3.0.10.0.1.dist-info/licenses/licenses/pystring-LICENSE
oiio_python-3.0.10.0.1.dist-info/licenses/licenses/libwebp-LICENSE
oiio_python-3.0.10.0.1.dist-info/licenses/licenses/openexr-LICENSE
oiio_python-3.0.10.0.1.dist-info/licenses/licenses/libtiff-LICENSE
oiio_python-3.0.10.0.1.dist-info/licenses/licenses/libjpegturbo-LICENSE
oiio_python-3.0.10.0.1.dist-info/licenses/licenses/giflib-LICENSE
oiio_python-3.0.10.0.1.dist-info/licenses/licenses/opencolorio-LICENSE
OpenImageIO/_tool_wrapper.py
OpenImageIO/__init__.py
OpenImageIO/OpenImageIO.cpython-311-darwin.so
OpenImageIO/tools/idiff
OpenImageIO/tools/igrep
OpenImageIO/tools/maketx
OpenImageIO/tools/iconvert
OpenImageIO/tools/oiiotool
OpenImageIO/tools/iinfo
OpenImageIO/.dylibs/libOpenImageIO.3.0.10.dylib
OpenImageIO/.dylibs/libtbbmalloc.2.10.dylib
OpenImageIO/.dylibs/libraw.dylib
OpenImageIO/.dylibs/libOpenImageIO_Util.3.0.10.dylib
OpenImageIO/.dylibs/libheif.1.16.2.dylib
OpenImageIO/.dylibs/libtbbmalloc_proxy.2.10.dylib
OpenImageIO/.dylibs/libtbb.12.10.dylib
OpenImageIO/.dylibs/libOpenColorIO.2.4.0.dylib
